{
  "kypt": 1,
  "kyp1": 10,
  "kyp2": 10,
  "kyi": 10,
  "kyd": 500,
  "kyth": 0,
  "kylimit": 900,

  "kppt": 1,
  "kpp1": 30,
  "kpp2": 30,
  "kpi": 0,
  "kpd": 300,
  "kpth": 0,
  "kplimit": 9000,

  "krpt": 1,
  "krp1": 0.4,
  "krp2": 0.4,
  "kri": 0,
  "krd": 5000,
  "krth": 0,
  "krlimit": 9000,

  "kvpt": 1,
  "kvp1": 300,
  "kvp2": 300,
  "kvi": 800,
  "kvd": 0,
  "kvth": 0,
  "kvlimit": 600,

  "CtrlSys_Pro_Min": 10,
  "CtrlSys_Fan_Min": 100,
  "CtrlSys_Pro_Max": 600,
  "CtrlSys_Pan_Max": 3000,
  "CtrlSys_pyth": 300,
  "CtrlSys_iyth": 2500,
  "CtrlSys_pcth": 600,
  "CtrlSys_icth": 50,
  "CtrlSys_pvth": 0.3,
  "CtrlSys_ivth": 3000,
  "CtrlSys_ppth":30,
  "CtrlSys_ipth":2500,
  "CtrlSys_prth":30,
  "CtrlSys_irth":2500,

  "AirscrewNCtrl":[200,200,200,200],
  "AirFrontscrewNCtrl": 0,
  "CtrlAllocatePara": [0.2,0.2,0.5],
  "Thro_Change_Limit": 70
}
